mopidy_local_images/web.py
mopidy_local_images/ext.conf
mopidy_local_images/library.py
mopidy_local_images/__init__.py
mopidy_local_images/www/index.html
Mopidy_Local_Images-1.0.0.dist-info/METADATA
Mopidy_Local_Images-1.0.0.dist-info/WHEEL
Mopidy_Local_Images-1.0.0.dist-info/entry_points.txt
Mopidy_Local_Images-1.0.0.dist-info/DESCRIPTION.rst
Mopidy_Local_Images-1.0.0.dist-info/top_level.txt
Mopidy_Local_Images-1.0.0.dist-info/metadata.json
Mopidy_Local_Images-1.0.0.dist-info/RECORD
