Metadata-Version: 2.0
Name: Mopidy-Local-Images
Version: 1.0.0
Summary: Mopidy local library proxy extension for handling embedded album art
Home-page: https://github.com/mopidy/mopidy-local-images
Author: Thomas Kemmer
Author-email: tkemmer@computer.org
License: Apache License, Version 2.0
Platform: UNKNOWN
Classifier: Environment :: No Input/Output (Daemon)
Classifier: Intended Audience :: End Users/Desktop
Classifier: License :: OSI Approved :: Apache Software License
Classifier: Operating System :: OS Independent
Classifier: Programming Language :: Python :: 2
Classifier: Topic :: Multimedia :: Sound/Audio :: Players
Requires-Dist: setuptools
Requires-Dist: Mopidy (>=1.1)
Requires-Dist: Pykka (>=1.1)
Requires-Dist: uritools (>=1.0)
